llama_index/llms/gemini/__init__.py
llama_index/llms/gemini/base.py
llama_index/llms/gemini/utils.py
flying_delta_llms_gemini-0.1.0.dist-info/METADATA
flying_delta_llms_gemini-0.1.0.dist-info/WHEEL
flying_delta_llms_gemini-0.1.0.dist-info/RECORD
